Aplos/AplosParser.py
Aplos/__init__.py
Aplos/exceptions.py
Aplos-1.1.dist-info/METADATA
Aplos-1.1.dist-info/RECORD
Aplos-1.1.dist-info/WHEEL
Aplos-1.1.dist-info/top_level.txt
tests/__init__.py
tests/test_det_errors.py
tests/test_dual_matrices.py
tests/test_file_read.py
tests/test_get_dim.py
tests/test_get_matrix.py
tests/test_get_vars.py
tests/test_read_matrices.py
tests/test_save_to_file.py
tests/test_text_init.py
