Metadata-Version: 2.1
Name: Aplos
Version: 1.1
Summary: A Linear Problem parser
Home-page: https://github.com/TsimpDim/Aplos
Author: Tsimpitas Dimitris
Author-email: dimitristsimpitas@gmail.com
License: UNKNOWN
Platform: UNKNOWN
Classifier: Programming Language :: Python :: 3
Classifier: License :: OSI Approved :: GNU General Public License v3 (GPLv3)
Classifier: Operating System :: OS Independent
